[
  {
    "name": "TCGGGGTGGGGGATGGGAGGG",
    "modelSeeds": [
      42
    ],
    "sequences": [
      {
        "proteinChain": {
          "sequence": "DELCPVCGDKVSGYHYGLLTCESCKGFFKRTVQNNKHYTCTESQSCKIDKTQRKRCPFCRFQKCLTVGMRLEAVRADRMRGGRNKFGPMYKRDRALKQQKKA",
          "count": 1,
          "maxTemplateDate": "2025-02-03"
        }
      },
      {
        "dnaSequence": {
          "sequence": "TCGGGGTGGGGGATGGGAGGG",
          "count": 1
        }
      },
      {
        "dnaSequence": {
          "sequence": "CCCTCCCATCCCCCACCCCGA",
          "count": 1
        }
      },
      {
        "ion": {
          "ion": "ZN",
          "count": 2
        }
      }
    ],
    "dialect": "alphafoldserver",
    "version": 1
  },
  {
    "name": "GCTCAATATGCGTACCGCATG",
    "modelSeeds": [
      42
    ],
    "sequences": [
      {
        "proteinChain": {
          "sequence": "DELCPVCGDKVSGYHYGLLTCESCKGFFKRTVQNNKHYTCTESQSCKIDKTQRKRCPFCRFQKCLTVGMRLEAVRADRMRGGRNKFGPMYKRDRALKQQKKA",
          "count": 1,
          "maxTemplateDate": "2025-02-03"
        }
      },
      {
        "dnaSequence": {
          "sequence": "GCTCAATATGCGTACCGCATG",
          "count": 1
        }
      },
      {
        "dnaSequence": {
          "sequence": "CATGCGGTACGCATATTGAGC",
          "count": 1
        }
      },
      {
        "ion": {
          "ion": "ZN",
          "count": 2
        }
      }
    ],
    "dialect": "alphafoldserver",
    "version": 1
  },
  {
    "name": "ACTCTACTATTTATCTAGGAG",
    "modelSeeds": [
      42
    ],
    "sequences": [
      {
        "proteinChain": {
          "sequence": "DELCPVCGDKVSGYHYGLLTCESCKGFFKRTVQNNKHYTCTESQSCKIDKTQRKRCPFCRFQKCLTVGMRLEAVRADRMRGGRNKFGPMYKRDRALKQQKKA",
          "count": 1,
          "maxTemplateDate": "2025-02-03"
        }
      },
      {
        "dnaSequence": {
          "sequence": "ACTCTACTATTTATCTAGGAG",
          "count": 1
        }
      },
      {
        "dnaSequence": {
          "sequence": "CTCCTAGATAAATAGTAGAGT",
          "count": 1
        }
      },
      {
        "ion": {
          "ion": "ZN",
          "count": 2
        }
      }
    ],
    "dialect": "alphafoldserver",
    "version": 1
  },
  {
    "name": "AGCCGCGAGGTTTACGCCCTA",
    "modelSeeds": [
      42
    ],
    "sequences": [
      {
        "proteinChain": {
          "sequence": "DELCPVCGDKVSGYHYGLLTCESCKGFFKRTVQNNKHYTCTESQSCKIDKTQRKRCPFCRFQKCLTVGMRLEAVRADRMRGGRNKFGPMYKRDRALKQQKKA",
          "count": 1,
          "maxTemplateDate": "2025-02-03"
        }
      },
      {
        "dnaSequence": {
          "sequence": "AGCCGCGAGGTTTACGCCCTA",
          "count": 1
        }
      },
      {
        "dnaSequence": {
          "sequence": "TAGGGCGTAAACCTCGCGGCT",
          "count": 1
        }
      },
      {
        "ion": {
          "ion": "ZN",
          "count": 2
        }
      }
    ],
    "dialect": "alphafoldserver",
    "version": 1
  },
  {
    "name": "GGCGTCCACTTGAAGGCTTCA",
    "modelSeeds": [
      42
    ],
    "sequences": [
      {
        "proteinChain": {
          "sequence": "DELCPVCGDKVSGYHYGLLTCESCKGFFKRTVQNNKHYTCTESQSCKIDKTQRKRCPFCRFQKCLTVGMRLEAVRADRMRGGRNKFGPMYKRDRALKQQKKA",
          "count": 1,
          "maxTemplateDate": "2025-02-03"
        }
      },
      {
        "dnaSequence": {
          "sequence": "GGCGTCCACTTGAAGGCTTCA",
          "count": 1
        }
      },
      {
        "dnaSequence": {
          "sequence": "TGAAGCCTTCAAGTGGACGCC",
          "count": 1
        }
      },
      {
        "ion": {
          "ion": "ZN",
          "count": 2
        }
      }
    ],
    "dialect": "alphafoldserver",
    "version": 1
  },
  {
    "name": "TTTGAGTTTACGGGAGTTTAA",
    "modelSeeds": [
      42
    ],
    "sequences": [
      {
        "proteinChain": {
          "sequence": "DELCPVCGDKVSGYHYGLLTCESCKGFFKRTVQNNKHYTCTESQSCKIDKTQRKRCPFCRFQKCLTVGMRLEAVRADRMRGGRNKFGPMYKRDRALKQQKKA",
          "count": 1,
          "maxTemplateDate": "2025-02-03"
        }
      },
      {
        "dnaSequence": {
          "sequence": "TTTGAGTTTACGGGAGTTTAA",
          "count": 1
        }
      },
      {
        "dnaSequence": {
          "sequence": "TTAAACTCCCGTAAACTCAAA",
          "count": 1
        }
      },
      {
        "ion": {
          "ion": "ZN",
          "count": 2
        }
      }
    ],
    "dialect": "alphafoldserver",
    "version": 1
  },
  {
    "name": "TGTTGATTAGCACTATCCCTC",
    "modelSeeds": [
      42
    ],
    "sequences": [
      {
        "proteinChain": {
          "sequence": "DELCPVCGDKVSGYHYGLLTCESCKGFFKRTVQNNKHYTCTESQSCKIDKTQRKRCPFCRFQKCLTVGMRLEAVRADRMRGGRNKFGPMYKRDRALKQQKKA",
          "count": 1,
          "maxTemplateDate": "2025-02-03"
        }
      },
      {
        "dnaSequence": {
          "sequence": "TGTTGATTAGCACTATCCCTC",
          "count": 1
        }
      },
      {
        "dnaSequence": {
          "sequence": "GAGGGATAGTGCTAATCAACA",
          "count": 1
        }
      },
      {
        "ion": {
          "ion": "ZN",
          "count": 2
        }
      }
    ],
    "dialect": "alphafoldserver",
    "version": 1
  },
  {
    "name": "GATGATGTTAGGCGAAGTTTT",
    "modelSeeds": [
      42
    ],
    "sequences": [
      {
        "proteinChain": {
          "sequence": "DELCPVCGDKVSGYHYGLLTCESCKGFFKRTVQNNKHYTCTESQSCKIDKTQRKRCPFCRFQKCLTVGMRLEAVRADRMRGGRNKFGPMYKRDRALKQQKKA",
          "count": 1,
          "maxTemplateDate": "2025-02-03"
        }
      },
      {
        "dnaSequence": {
          "sequence": "GATGATGTTAGGCGAAGTTTT",
          "count": 1
        }
      },
      {
        "dnaSequence": {
          "sequence": "AAAACTTCGCCTAACATCATC",
          "count": 1
        }
      },
      {
        "ion": {
          "ion": "ZN",
          "count": 2
        }
      }
    ],
    "dialect": "alphafoldserver",
    "version": 1
  },
  {
    "name": "AAGAGGTACGGAGACATCTCC",
    "modelSeeds": [
      42
    ],
    "sequences": [
      {
        "proteinChain": {
          "sequence": "DELCPVCGDKVSGYHYGLLTCESCKGFFKRTVQNNKHYTCTESQSCKIDKTQRKRCPFCRFQKCLTVGMRLEAVRADRMRGGRNKFGPMYKRDRALKQQKKA",
          "count": 1,
          "maxTemplateDate": "2025-02-03"
        }
      },
      {
        "dnaSequence": {
          "sequence": "AAGAGGTACGGAGACATCTCC",
          "count": 1
        }
      },
      {
        "dnaSequence": {
          "sequence": "GGAGATGTCTCCGTACCTCTT",
          "count": 1
        }
      },
      {
        "ion": {
          "ion": "ZN",
          "count": 2
        }
      }
    ],
    "dialect": "alphafoldserver",
    "version": 1
  },
  {
    "name": "CAGTTTATGTGACCTTCTCTG",
    "modelSeeds": [
      42
    ],
    "sequences": [
      {
        "proteinChain": {
          "sequence": "DELCPVCGDKVSGYHYGLLTCESCKGFFKRTVQNNKHYTCTESQSCKIDKTQRKRCPFCRFQKCLTVGMRLEAVRADRMRGGRNKFGPMYKRDRALKQQKKA",
          "count": 1,
          "maxTemplateDate": "2025-02-03"
        }
      },
      {
        "dnaSequence": {
          "sequence": "CAGTTTATGTGACCTTCTCTG",
          "count": 1
        }
      },
      {
        "dnaSequence": {
          "sequence": "CAGAGAAGGTCACATAAACTG",
          "count": 1
        }
      },
      {
        "ion": {
          "ion": "ZN",
          "count": 2
        }
      }
    ],
    "dialect": "alphafoldserver",
    "version": 1
  },
  {
    "name": "CACAGTAGCCTAGGATGTCGT",
    "modelSeeds": [
      42
    ],
    "sequences": [
      {
        "proteinChain": {
          "sequence": "DELCPVCGDKVSGYHYGLLTCESCKGFFKRTVQNNKHYTCTESQSCKIDKTQRKRCPFCRFQKCLTVGMRLEAVRADRMRGGRNKFGPMYKRDRALKQQKKA",
          "count": 1,
          "maxTemplateDate": "2025-02-03"
        }
      },
      {
        "dnaSequence": {
          "sequence": "CACAGTAGCCTAGGATGTCGT",
          "count": 1
        }
      },
      {
        "dnaSequence": {
          "sequence": "ACGACATCCTAGGCTACTGTG",
          "count": 1
        }
      },
      {
        "ion": {
          "ion": "ZN",
          "count": 2
        }
      }
    ],
    "dialect": "alphafoldserver",
    "version": 1
  },
  {
    "name": "TGTGAGTCTCAATAAAAACGC",
    "modelSeeds": [
      42
    ],
    "sequences": [
      {
        "proteinChain": {
          "sequence": "DELCPVCGDKVSGYHYGLLTCESCKGFFKRTVQNNKHYTCTESQSCKIDKTQRKRCPFCRFQKCLTVGMRLEAVRADRMRGGRNKFGPMYKRDRALKQQKKA",
          "count": 1,
          "maxTemplateDate": "2025-02-03"
        }
      },
      {
        "dnaSequence": {
          "sequence": "TGTGAGTCTCAATAAAAACGC",
          "count": 1
        }
      },
      {
        "dnaSequence": {
          "sequence": "GCGTTTTTATTGAGACTCACA",
          "count": 1
        }
      },
      {
        "ion": {
          "ion": "ZN",
          "count": 2
        }
      }
    ],
    "dialect": "alphafoldserver",
    "version": 1
  },
  {
    "name": "AAACCGCCTCCATAGTGCTGT",
    "modelSeeds": [
      42
    ],
    "sequences": [
      {
        "proteinChain": {
          "sequence": "DELCPVCGDKVSGYHYGLLTCESCKGFFKRTVQNNKHYTCTESQSCKIDKTQRKRCPFCRFQKCLTVGMRLEAVRADRMRGGRNKFGPMYKRDRALKQQKKA",
          "count": 1,
          "maxTemplateDate": "2025-02-03"
        }
      },
      {
        "dnaSequence": {
          "sequence": "AAACCGCCTCCATAGTGCTGT",
          "count": 1
        }
      },
      {
        "dnaSequence": {
          "sequence": "ACAGCACTATGGAGGCGGTTT",
          "count": 1
        }
      },
      {
        "ion": {
          "ion": "ZN",
          "count": 2
        }
      }
    ],
    "dialect": "alphafoldserver",
    "version": 1
  },
  {
    "name": "ATGCAAAGGAATTCCAGTCCT",
    "modelSeeds": [
      42
    ],
    "sequences": [
      {
        "proteinChain": {
          "sequence": "DELCPVCGDKVSGYHYGLLTCESCKGFFKRTVQNNKHYTCTESQSCKIDKTQRKRCPFCRFQKCLTVGMRLEAVRADRMRGGRNKFGPMYKRDRALKQQKKA",
          "count": 1,
          "maxTemplateDate": "2025-02-03"
        }
      },
      {
        "dnaSequence": {
          "sequence": "ATGCAAAGGAATTCCAGTCCT",
          "count": 1
        }
      },
      {
        "dnaSequence": {
          "sequence": "AGGACTGGAATTCCTTTGCAT",
          "count": 1
        }
      },
      {
        "ion": {
          "ion": "ZN",
          "count": 2
        }
      }
    ],
    "dialect": "alphafoldserver",
    "version": 1
  },
  {
    "name": "CACCTCCGCCAGGCATACACA",
    "modelSeeds": [
      42
    ],
    "sequences": [
      {
        "proteinChain": {
          "sequence": "DELCPVCGDKVSGYHYGLLTCESCKGFFKRTVQNNKHYTCTESQSCKIDKTQRKRCPFCRFQKCLTVGMRLEAVRADRMRGGRNKFGPMYKRDRALKQQKKA",
          "count": 1,
          "maxTemplateDate": "2025-02-03"
        }
      },
      {
        "dnaSequence": {
          "sequence": "CACCTCCGCCAGGCATACACA",
          "count": 1
        }
      },
      {
        "dnaSequence": {
          "sequence": "TGTGTATGCCTGGCGGAGGTG",
          "count": 1
        }
      },
      {
        "ion": {
          "ion": "ZN",
          "count": 2
        }
      }
    ],
    "dialect": "alphafoldserver",
    "version": 1
  },
  {
    "name": "CAGGAACGGGCGTGCTCCTTA",
    "modelSeeds": [
      42
    ],
    "sequences": [
      {
        "proteinChain": {
          "sequence": "DELCPVCGDKVSGYHYGLLTCESCKGFFKRTVQNNKHYTCTESQSCKIDKTQRKRCPFCRFQKCLTVGMRLEAVRADRMRGGRNKFGPMYKRDRALKQQKKA",
          "count": 1,
          "maxTemplateDate": "2025-02-03"
        }
      },
      {
        "dnaSequence": {
          "sequence": "CAGGAACGGGCGTGCTCCTTA",
          "count": 1
        }
      },
      {
        "dnaSequence": {
          "sequence": "TAAGGAGCACGCCCGTTCCTG",
          "count": 1
        }
      },
      {
        "ion": {
          "ion": "ZN",
          "count": 2
        }
      }
    ],
    "dialect": "alphafoldserver",
    "version": 1
  },
  {
    "name": "TGACGTATAATGGAAACACCT",
    "modelSeeds": [
      42
    ],
    "sequences": [
      {
        "proteinChain": {
          "sequence": "DELCPVCGDKVSGYHYGLLTCESCKGFFKRTVQNNKHYTCTESQSCKIDKTQRKRCPFCRFQKCLTVGMRLEAVRADRMRGGRNKFGPMYKRDRALKQQKKA",
          "count": 1,
          "maxTemplateDate": "2025-02-03"
        }
      },
      {
        "dnaSequence": {
          "sequence": "TGACGTATAATGGAAACACCT",
          "count": 1
        }
      },
      {
        "dnaSequence": {
          "sequence": "AGGTGTTTCCATTATACGTCA",
          "count": 1
        }
      },
      {
        "ion": {
          "ion": "ZN",
          "count": 2
        }
      }
    ],
    "dialect": "alphafoldserver",
    "version": 1
  },
  {
    "name": "TACGCGCATAGCGGTGCAACT",
    "modelSeeds": [
      42
    ],
    "sequences": [
      {
        "proteinChain": {
          "sequence": "DELCPVCGDKVSGYHYGLLTCESCKGFFKRTVQNNKHYTCTESQSCKIDKTQRKRCPFCRFQKCLTVGMRLEAVRADRMRGGRNKFGPMYKRDRALKQQKKA",
          "count": 1,
          "maxTemplateDate": "2025-02-03"
        }
      },
      {
        "dnaSequence": {
          "sequence": "TACGCGCATAGCGGTGCAACT",
          "count": 1
        }
      },
      {
        "dnaSequence": {
          "sequence": "AGTTGCACCGCTATGCGCGTA",
          "count": 1
        }
      },
      {
        "ion": {
          "ion": "ZN",
          "count": 2
        }
      }
    ],
    "dialect": "alphafoldserver",
    "version": 1
  },
  {
    "name": "ATGTCTCTATCCTATTGGCAT",
    "modelSeeds": [
      42
    ],
    "sequences": [
      {
        "proteinChain": {
          "sequence": "DELCPVCGDKVSGYHYGLLTCESCKGFFKRTVQNNKHYTCTESQSCKIDKTQRKRCPFCRFQKCLTVGMRLEAVRADRMRGGRNKFGPMYKRDRALKQQKKA",
          "count": 1,
          "maxTemplateDate": "2025-02-03"
        }
      },
      {
        "dnaSequence": {
          "sequence": "ATGTCTCTATCCTATTGGCAT",
          "count": 1
        }
      },
      {
        "dnaSequence": {
          "sequence": "ATGCCAATAGGATAGAGACAT",
          "count": 1
        }
      },
      {
        "ion": {
          "ion": "ZN",
          "count": 2
        }
      }
    ],
    "dialect": "alphafoldserver",
    "version": 1
  },
  {
    "name": "GCGGCTTTCATTATAATTCCT",
    "modelSeeds": [
      42
    ],
    "sequences": [
      {
        "proteinChain": {
          "sequence": "DELCPVCGDKVSGYHYGLLTCESCKGFFKRTVQNNKHYTCTESQSCKIDKTQRKRCPFCRFQKCLTVGMRLEAVRADRMRGGRNKFGPMYKRDRALKQQKKA",
          "count": 1,
          "maxTemplateDate": "2025-02-03"
        }
      },
      {
        "dnaSequence": {
          "sequence": "GCGGCTTTCATTATAATTCCT",
          "count": 1
        }
      },
      {
        "dnaSequence": {
          "sequence": "AGGAATTATAATGAAAGCCGC",
          "count": 1
        }
      },
      {
        "ion": {
          "ion": "ZN",
          "count": 2
        }
      }
    ],
    "dialect": "alphafoldserver",
    "version": 1
  },
  {
    "name": "AGGTGCCCGCGAGACAGAATA",
    "modelSeeds": [
      42
    ],
    "sequences": [
      {
        "proteinChain": {
          "sequence": "DELCPVCGDKVSGYHYGLLTCESCKGFFKRTVQNNKHYTCTESQSCKIDKTQRKRCPFCRFQKCLTVGMRLEAVRADRMRGGRNKFGPMYKRDRALKQQKKA",
          "count": 1,
          "maxTemplateDate": "2025-02-03"
        }
      },
      {
        "dnaSequence": {
          "sequence": "AGGTGCCCGCGAGACAGAATA",
          "count": 1
        }
      },
      {
        "dnaSequence": {
          "sequence": "TATTCTGTCTCGCGGGCACCT",
          "count": 1
        }
      },
      {
        "ion": {
          "ion": "ZN",
          "count": 2
        }
      }
    ],
    "dialect": "alphafoldserver",
    "version": 1
  },
  {
    "name": "AAATTGAAATCCTCAATATCT",
    "modelSeeds": [
      42
    ],
    "sequences": [
      {
        "proteinChain": {
          "sequence": "DELCPVCGDKVSGYHYGLLTCESCKGFFKRTVQNNKHYTCTESQSCKIDKTQRKRCPFCRFQKCLTVGMRLEAVRADRMRGGRNKFGPMYKRDRALKQQKKA",
          "count": 1,
          "maxTemplateDate": "2025-02-03"
        }
      },
      {
        "dnaSequence": {
          "sequence": "AAATTGAAATCCTCAATATCT",
          "count": 1
        }
      },
      {
        "dnaSequence": {
          "sequence": "AGATATTGAGGATTTCAATTT",
          "count": 1
        }
      },
      {
        "ion": {
          "ion": "ZN",
          "count": 2
        }
      }
    ],
    "dialect": "alphafoldserver",
    "version": 1
  },
  {
    "name": "CATGGCACCGTGCATGTCTAT",
    "modelSeeds": [
      42
    ],
    "sequences": [
      {
        "proteinChain": {
          "sequence": "DELCPVCGDKVSGYHYGLLTCESCKGFFKRTVQNNKHYTCTESQSCKIDKTQRKRCPFCRFQKCLTVGMRLEAVRADRMRGGRNKFGPMYKRDRALKQQKKA",
          "count": 1,
          "maxTemplateDate": "2025-02-03"
        }
      },
      {
        "dnaSequence": {
          "sequence": "CATGGCACCGTGCATGTCTAT",
          "count": 1
        }
      },
      {
        "dnaSequence": {
          "sequence": "ATAGACATGCACGGTGCCATG",
          "count": 1
        }
      },
      {
        "ion": {
          "ion": "ZN",
          "count": 2
        }
      }
    ],
    "dialect": "alphafoldserver",
    "version": 1
  },
  {
    "name": "CCCTATTACTACTGCCTACAG",
    "modelSeeds": [
      42
    ],
    "sequences": [
      {
        "proteinChain": {
          "sequence": "DELCPVCGDKVSGYHYGLLTCESCKGFFKRTVQNNKHYTCTESQSCKIDKTQRKRCPFCRFQKCLTVGMRLEAVRADRMRGGRNKFGPMYKRDRALKQQKKA",
          "count": 1,
          "maxTemplateDate": "2025-02-03"
        }
      },
      {
        "dnaSequence": {
          "sequence": "CCCTATTACTACTGCCTACAG",
          "count": 1
        }
      },
      {
        "dnaSequence": {
          "sequence": "CTGTAGGCAGTAGTAATAGGG",
          "count": 1
        }
      },
      {
        "ion": {
          "ion": "ZN",
          "count": 2
        }
      }
    ],
    "dialect": "alphafoldserver",
    "version": 1
  },
  {
    "name": "ACGTCTAATCGTTCTATGTCA",
    "modelSeeds": [
      42
    ],
    "sequences": [
      {
        "proteinChain": {
          "sequence": "DELCPVCGDKVSGYHYGLLTCESCKGFFKRTVQNNKHYTCTESQSCKIDKTQRKRCPFCRFQKCLTVGMRLEAVRADRMRGGRNKFGPMYKRDRALKQQKKA",
          "count": 1,
          "maxTemplateDate": "2025-02-03"
        }
      },
      {
        "dnaSequence": {
          "sequence": "ACGTCTAATCGTTCTATGTCA",
          "count": 1
        }
      },
      {
        "dnaSequence": {
          "sequence": "TGACATAGAACGATTAGACGT",
          "count": 1
        }
      },
      {
        "ion": {
          "ion": "ZN",
          "count": 2
        }
      }
    ],
    "dialect": "alphafoldserver",
    "version": 1
  },
  {
    "name": "TTGCCGAACTACCATGTGTGA",
    "modelSeeds": [
      42
    ],
    "sequences": [
      {
        "proteinChain": {
          "sequence": "DELCPVCGDKVSGYHYGLLTCESCKGFFKRTVQNNKHYTCTESQSCKIDKTQRKRCPFCRFQKCLTVGMRLEAVRADRMRGGRNKFGPMYKRDRALKQQKKA",
          "count": 1,
          "maxTemplateDate": "2025-02-03"
        }
      },
      {
        "dnaSequence": {
          "sequence": "TTGCCGAACTACCATGTGTGA",
          "count": 1
        }
      },
      {
        "dnaSequence": {
          "sequence": "TCACACATGGTAGTTCGGCAA",
          "count": 1
        }
      },
      {
        "ion": {
          "ion": "ZN",
          "count": 2
        }
      }
    ],
    "dialect": "alphafoldserver",
    "version": 1
  },
  {
    "name": "TTGACGTAACCCTCTGCATCT",
    "modelSeeds": [
      42
    ],
    "sequences": [
      {
        "proteinChain": {
          "sequence": "DELCPVCGDKVSGYHYGLLTCESCKGFFKRTVQNNKHYTCTESQSCKIDKTQRKRCPFCRFQKCLTVGMRLEAVRADRMRGGRNKFGPMYKRDRALKQQKKA",
          "count": 1,
          "maxTemplateDate": "2025-02-03"
        }
      },
      {
        "dnaSequence": {
          "sequence": "TTGACGTAACCCTCTGCATCT",
          "count": 1
        }
      },
      {
        "dnaSequence": {
          "sequence": "AGATGCAGAGGGTTACGTCAA",
          "count": 1
        }
      },
      {
        "ion": {
          "ion": "ZN",
          "count": 2
        }
      }
    ],
    "dialect": "alphafoldserver",
    "version": 1
  },
  {
    "name": "CGTTTCAGGAGGAACGTTTGC",
    "modelSeeds": [
      42
    ],
    "sequences": [
      {
        "proteinChain": {
          "sequence": "DELCPVCGDKVSGYHYGLLTCESCKGFFKRTVQNNKHYTCTESQSCKIDKTQRKRCPFCRFQKCLTVGMRLEAVRADRMRGGRNKFGPMYKRDRALKQQKKA",
          "count": 1,
          "maxTemplateDate": "2025-02-03"
        }
      },
      {
        "dnaSequence": {
          "sequence": "CGTTTCAGGAGGAACGTTTGC",
          "count": 1
        }
      },
      {
        "dnaSequence": {
          "sequence": "GCAAACGTTCCTCCTGAAACG",
          "count": 1
        }
      },
      {
        "ion": {
          "ion": "ZN",
          "count": 2
        }
      }
    ],
    "dialect": "alphafoldserver",
    "version": 1
  },
  {
    "name": "ACTTTGCCTAAGGGGTTCGCC",
    "modelSeeds": [
      42
    ],
    "sequences": [
      {
        "proteinChain": {
          "sequence": "DELCPVCGDKVSGYHYGLLTCESCKGFFKRTVQNNKHYTCTESQSCKIDKTQRKRCPFCRFQKCLTVGMRLEAVRADRMRGGRNKFGPMYKRDRALKQQKKA",
          "count": 1,
          "maxTemplateDate": "2025-02-03"
        }
      },
      {
        "dnaSequence": {
          "sequence": "ACTTTGCCTAAGGGGTTCGCC",
          "count": 1
        }
      },
      {
        "dnaSequence": {
          "sequence": "GGCGAACCCCTTAGGCAAAGT",
          "count": 1
        }
      },
      {
        "ion": {
          "ion": "ZN",
          "count": 2
        }
      }
    ],
    "dialect": "alphafoldserver",
    "version": 1
  },
  {
    "name": "GACCGATCACCTTTCCAGGTG",
    "modelSeeds": [
      42
    ],
    "sequences": [
      {
        "proteinChain": {
          "sequence": "DELCPVCGDKVSGYHYGLLTCESCKGFFKRTVQNNKHYTCTESQSCKIDKTQRKRCPFCRFQKCLTVGMRLEAVRADRMRGGRNKFGPMYKRDRALKQQKKA",
          "count": 1,
          "maxTemplateDate": "2025-02-03"
        }
      },
      {
        "dnaSequence": {
          "sequence": "GACCGATCACCTTTCCAGGTG",
          "count": 1
        }
      },
      {
        "dnaSequence": {
          "sequence": "CACCTGGAAAGGTGATCGGTC",
          "count": 1
        }
      },
      {
        "ion": {
          "ion": "ZN",
          "count": 2
        }
      }
    ],
    "dialect": "alphafoldserver",
    "version": 1
  }
]